nosqllite/__init__.py
nosqllite/database.py
nosqllite/document.py
nosqllite/group.py
nosqllite-0.1.2.dist-info/licenses/LICENSE
nosqllite-0.1.2.dist-info/METADATA
nosqllite-0.1.2.dist-info/WHEEL
nosqllite-0.1.2.dist-info/top_level.txt
nosqllite-0.1.2.dist-info/RECORD
