Metadata-Version: 2.4
Name: nosqllite
Version: 0.1.2
Summary: A simple nosql data base
Home-page: https://github.com/AxelGard/nosqllite
Author: Axel Gard
Author-email: axel.gard@tutanota.com
License: MIT
Classifier: Development Status :: 3 - Alpha
Classifier: Topic :: Database
Classifier: Topic :: Database :: Database Engines/Servers
Classifier: Programming Language :: Python :: 3.8
Classifier: License :: OSI Approved :: MIT License
License-File: LICENSE
Provides-Extra: dev
Requires-Dist: pytest; extra == "dev"
Requires-Dist: black; extra == "dev"
Dynamic: author
Dynamic: author-email
Dynamic: classifier
Dynamic: description
Dynamic: description-content-type
Dynamic: home-page
Dynamic: license
Dynamic: license-file
Dynamic: provides-extra
Dynamic: summary
